MANIFEST.in
README.rst
setup.cfg
setup.py
tw2/__init__.py
tw2.jqplugins.chosen.egg-info/PKG-INFO
tw2.jqplugins.chosen.egg-info/SOURCES.txt
tw2.jqplugins.chosen.egg-info/dependency_links.txt
tw2.jqplugins.chosen.egg-info/entry_points.txt
tw2.jqplugins.chosen.egg-info/namespace_packages.txt
tw2.jqplugins.chosen.egg-info/not-zip-safe
tw2.jqplugins.chosen.egg-info/requires.txt
tw2.jqplugins.chosen.egg-info/top_level.txt
tw2/jqplugins/__init__.py
tw2/jqplugins/chosen/__init__.py
tw2/jqplugins/chosen/samples.py
tw2/jqplugins/chosen/widgets.py
tw2/jqplugins/chosen/static/chosen-sprite.png
tw2/jqplugins/chosen/static/chosen-sprite@2x.png
tw2/jqplugins/chosen/static/chosen.css
tw2/jqplugins/chosen/static/chosen.jquery.js
tw2/jqplugins/chosen/static/chosen.jquery.min.js
tw2/jqplugins/chosen/static/chosen.min.css