Metadata-Version: 1.1
Name: tw2.jqplugins.chosen
Version: 0.3
Summary: ToscaWidgets 2 SelectFields enhanced with the Chosen javascript library.
Home-page: https://github.com/toscawidgets/tw2.jqplugins.chosen
Author: Moritz Schlarb
Author-email: moschlar@metalabs.de
License: MIT
Keywords: toscawidgets.widgets
Platform: UNKNOWN
Classifier: Development Status :: 4 - Beta
Classifier: Environment :: Web Environment
Classifier: Environment :: Web Environment :: ToscaWidgets
Classifier: Topic :: Software Development :: Libraries :: Python Modules
Classifier: Topic :: Software Development :: Widget Sets
Classifier: Intended Audience :: Developers
Classifier: Operating System :: OS Independent
Classifier: Programming Language :: Python
